MANIFEST.in
README.md
setup.py
Flask_MailAlchemy.egg-info/PKG-INFO
Flask_MailAlchemy.egg-info/SOURCES.txt
Flask_MailAlchemy.egg-info/dependency_links.txt
Flask_MailAlchemy.egg-info/requires.txt
Flask_MailAlchemy.egg-info/top_level.txt
flask_mailalchemy/__init__.py
flask_mailalchemy/core.py
flask_mailalchemy/model.py
flask_mailalchemy/templates/mail/base.html
flask_mailalchemy/templates/mail/base.txt
flask_mailalchemy/templates/mail/hello_world.html
flask_mailalchemy/templates/mail/hello_world.txt
flask_mailalchemy/templates/mail/blocks/footer.html
flask_mailalchemy/templates/mail/blocks/footer.txt
flask_mailalchemy/templates/mail/blocks/greetings.html
flask_mailalchemy/templates/mail/blocks/greetings.txt
flask_mailalchemy/templates/mail/blocks/header.html
flask_mailalchemy/templates/mail/blocks/header.txt
flask_mailalchemy/templates/mail/blocks/hello_world.html
flask_mailalchemy/templates/mail/blocks/hello_world.txt
flask_mailalchemy/templates/mail/blocks/sign_off.html
flask_mailalchemy/templates/mail/blocks/sign_off.txt