Metadata-Version: 2.1
Name: Flask-MailAlchemy
Version: 0.4
Summary: SQLAlchemy based e-mail sending extension for Flask
Home-page: https://github.com/gerelorant/flask-mailalchemy
Author: Gere Lóránt
Author-email: gerelorant@gmail.com
License: MIT
Platform: UNKNOWN
